Workbook
Name g_2026: 'Hypotheses'!$C$3
Name g_2027: 'Hypotheses'!$C$4
Name g_2028: 'Hypotheses'!$C$5
Name g_2029: 'Hypotheses'!$C$6
Name g_2030: 'Hypotheses'!$C$7
Name marge_2026: 'Hypotheses'!$C$8
Name marge_2027: 'Hypotheses'!$C$9
Name marge_2028: 'Hypotheses'!$C$10
Name marge_2029: 'Hypotheses'!$C$11
Name marge_2030: 'Hypotheses'!$C$12
Name tauxIS_2026: 'Hypotheses'!$C$13
Name tauxIS_2027: 'Hypotheses'!$C$14
Name tauxIS_2028: 'Hypotheses'!$C$15
Name tauxIS_2029: 'Hypotheses'!$C$16
Name tauxIS_2030: 'Hypotheses'!$C$17
Name capexRatio: 'Hypotheses'!$C$18
Name dureeAmort: 'Hypotheses'!$C$19
Name tauxDette: 'Hypotheses'!$C$20
Name tauxCash: 'Hypotheses'!$C$21
Name tauxLease: 'Hypotheses'!$C$22
Name rachatPct: 'Hypotheses'!$C$23
Name tauxDistrib: 'Hypotheses'!$C$24
Name gTerminal: 'Hypotheses'!$C$25
Name margeTerminale: 'Hypotheses'!$C$26
Name partMinos: 'Hypotheses'!$C$27
Name pub_ca: 'Historique'!$B$3
Name pub_margeBrute: 'Historique'!$B$4
Name pub_ebitda: 'Historique'!$B$5
Name pub_da: 'Historique'!$B$6
Name pub_ebit: 'Historique'!$B$7
Name pub_finNet: 'Historique'!$B$8
Name pub_avantImpot: 'Historique'!$B$9
Name pub_impot: 'Historique'!$B$10
Name pub_minoritaires: 'Historique'!$B$11
Name pub_net: 'Historique'!$B$12
Name impotRet: 'Historique'!$D$26
Name ajPub_ebitda: 'Historique'!$B$33
Name ajPub_ebit: 'Historique'!$C$33
Name ajPub_net: 'Historique'!$D$33
Name CA_2025: 'Modele'!$B$3
Name CA_2026: 'Modele'!$C$3
Name CA_2027: 'Modele'!$D$3
Name CA_2028: 'Modele'!$E$3
Name CA_2029: 'Modele'!$F$3
Name CA_2030: 'Modele'!$G$3
Name dette_2025: 'Modele'!$B$11
Name dette_2026: 'Modele'!$C$11
Name dette_2027: 'Modele'!$D$11
Name dette_2028: 'Modele'!$E$11
Name dette_2029: 'Modele'!$F$11
Name dette_2030: 'Modele'!$G$11
Name cash_2025: 'Modele'!$B$12
Name cash_2026: 'Modele'!$C$12
Name cash_2027: 'Modele'!$D$12
Name cash_2028: 'Modele'!$E$12
Name cash_2029: 'Modele'!$F$12
Name cash_2030: 'Modele'!$G$12

Sheet Lisez-moi
A1: Complexe SA — moteur v1.0.0 — empreinte daaf23ea1ee0
A3: Ce que contient ce fichier | B3: Les FORMULES du moteur, pas ses resultats. Chaque cellule calculee est une formule ecrite sur des variables nommees, lisible et modifiable.
A4: Le test integre | B4: Colonne 'moteur' = la valeur produite par engine/model.py. La feuille Controles compare formule et moteur ligne a ligne : un ecart s'affiche a l'ouverture.
A5: Peremption | B5: Une hypothese de rang 'guidance' ne vaut QUE pour son exercice. Au-dela le moteur bascule sur le normatif - visible dans la colonne rang de la feuille Modele.
A6: Rang du resultat financier | B6: 1 = detail publie par instrument. 2 = taux appliques aux postes de bilan decomposes. 3 = spread normatif sur la dette nette. La valeur est retournee AVEC son rang.
A7: Base Omnium | B7: publie + vrais one-offs nets d'impot. L'ajuste du management ajoute en plus les recurrents-deguises : c'est le coin, et Omnium le GARDE.
A8: Si l'empreinte ne correspond plus | B8: Les entrees ont change depuis la generation : cette feuille est perimee, regenerez-la.
A10: Devise de reporting | B10: EUR
A11: Devise de cotation | B11: EUR
A12: Cours | B12: 47.0 au 2026-08-22

Sheet Hypotheses
A1: MOTEURS — toute cellule projetee est pilotee par l'un d'eux
A2: moteur | B2: variable | C2: valeur | D2: rang | E2: expire | F2: justification / source
A3: Croissance du CA 2026 | B3: g_2026 | C3: 0.03 | D3: guidance | E3: 2026 | F3: Guidance FY26 : croissance organique +2 a +4 %
A4: Croissance du CA 2027 | B4: g_2027 | C4: -0.06 | D4: implicite | E4: — | F4: Perte du contrat Delta (25 % du CA de la division Nord), non renouvele au 30/06/2027
A5: Croissance du CA 2028 | B5: g_2028 | C5: 0.04 | D5: normatif | E5: — | F5: Retour a la croissance de marche apres l'effet de base
A6: Croissance du CA 2029 | B6: g_2029 | C6: 0.045 | D6: normatif | E6: — | F6: Retour a la croissance de marche apres l'effet de base
A7: Croissance du CA 2030 | B7: g_2030 | C7: 0.045 | D7: normatif | E7: — | F7: Retour a la croissance de marche apres l'effet de base
A8: Marge d'EBITDA 2026 | B8: marge_2026 | C8: 0.192 | D8: guidance | E8: 2026 | F8: Guidance FY26 : marge d'EBITDA ajustee 19 a 19,5 %
A9: Marge d'EBITDA 2027 | B9: marge_2027 | C9: 0.15 | D9: implicite | E9: — | F9: Effet de levier operationnel inverse sur la perte du contrat Delta, couts fixes non ajustables a court terme
A10: Marge d'EBITDA 2028 | B10: marge_2028 | C10: 0.178 | D10: implicite | E10: — | F10: Redressement progressif apres restructuration du perimetre Nord
A11: Marge d'EBITDA 2029 | B11: marge_2029 | C11: 0.19 | D11: normatif | E11: — | F11: Retour au niveau de marge historique
A12: Marge d'EBITDA 2030 | B12: marge_2030 | C12: 0.195 | D12: normatif | E12: — | F12: Retour au niveau de marge historique
A13: Taux d'impot 2026 | B13: tauxIS_2026 | C13: 0.27 | D13: guidance | E13: 2026 | F13: Taux effectif guide 26-28 % pour FY26
A14: Taux d'impot 2027 | B14: tauxIS_2027 | C14: 0.285 | D14: normatif | E14: — | F14: Taux effectif observe nettoye des elements discrets, moyenne 3 ans, releve de 1,5 pt par la reforme fiscale votee en 2026
A15: Taux d'impot 2028 | B15: tauxIS_2028 | C15: 0.285 | D15: normatif | E15: — | F15: Taux effectif observe nettoye des elements discrets, moyenne 3 ans, releve de 1,5 pt par la reforme fiscale votee en 2026
A16: Taux d'impot 2029 | B16: tauxIS_2029 | C16: 0.285 | D16: normatif | E16: — | F16: Taux effectif observe nettoye des elements discrets, moyenne 3 ans, releve de 1,5 pt par la reforme fiscale votee en 2026
A17: Taux d'impot 2030 | B17: tauxIS_2030 | C17: 0.285 | D17: normatif | E17: — | F17: Taux effectif observe nettoye des elements discrets, moyenne 3 ans, releve de 1,5 pt par la reforme fiscale votee en 2026
A18: Capex / CA | B18: capexRatio | C18: 0.055 | D18: normatif | E18: — | F18: Ratio de capex normatif, moyenne des 3 derniers exercices
A19: Duree d'amortissement | B19: dureeAmort | C19: 9 | D19: normatif | E19: — | F19: Duree implicite = immobilisations brutes / dotation courante
A20: Taux sur dette brute | B20: tauxDette | C20: 0.048 | D20: rang 2 | E20: — | F20: Rang 2 : taux appliques aux postes de bilan decomposes, faute de detail publie par instrument
A21: Taux sur tresorerie | B21: tauxCash | C21: 0.018 | D21: rang 2 | E21: — | F21: Rang 2 : taux appliques aux postes de bilan decomposes, faute de detail publie par instrument
A22: Taux sur dette locative | B22: tauxLease | C22: 0.038 | D22: rang 2 | E22: — | F22: Rang 2 : taux appliques aux postes de bilan decomposes, faute de detail publie par instrument
A23: Rachat d'actions / an | B23: rachatPct | C23: 0.008 | D23: implicite | E23: — | F23: Rachats limites a la neutralisation de la dilution, aucun programme annonce
A24: Taux de distribution | B24: tauxDistrib | C24: 0.25 | D24: normatif | E24: — | F24: Politique de dividende : 25 % du resultat net
A25: Croissance terminale | B25: gTerminal | C25: 0.03 | D25: normatif | E25: — | F25: Au-dela de l'horizon pose, convergence vers ces valeurs
... A27: Minoritaires / resultat | B27: partMinos | C27: -0.275 | D27: normatif | E27: — | F27: Part des minoritaires observee au dernier exercice publie, reconduite

Sheet Historique
A1: ECHELLE PUBLIEE 2025-FY — un modele unique, les barreaux non publies restent vides
A2: barreau | B2: publie
A3: ca | B3: 2000
A4: margeBrute | B4: 1100
A5: ebitda | B5: 380
A6: da | B6: -190
A7: ebit | B7: 190
A8: finNet | B8: -48
A9: avantImpot | B9: 142
A10: impot | B10: -40
A11: minoritaires | B11: -22
A12: net | B12: 80
A14: IDENTITES DE L'ECHELLE
A15: ebitda + da = ebit | B15: =pub_ebitda+pub_da-pub_ebit | C15: =IF(ABS(B15)<=MAX(1,ABS(pub_ebit)*0.005),"OK","ECART")
A16: ebit + finNet = avantImpot | B16: =pub_ebit+pub_finNet-pub_avantImpot | C16: =IF(ABS(B16)<=MAX(1,ABS(pub_avantImpot)*0.005),"OK","ECART")
A17: avantImpot + impot + minoritaires = net | B17: =pub_avantImpot+pub_impot+pub_minoritaires-pub_net | C17: =IF(ABS(B17)<=MAX(1,ABS(pub_net)*0.005),"OK","ECART")
A19: RETRAITEMENTS — la table de l'emetteur, ligne a ligne
A20: ligne | B20: ebitda | C20: ebit | D20: net | E20: classe | F20: origine | G20: libelle
A21: restructuration-plan-2025 | B21: 45 | C21: 45 | D21: 45 | E21: oneOff | F21: emetteur | G21: One-off restructuring plan announced in 2025
A22: beta-ppa-amort | B22: 0 | C22: 42 | D22: 42 | E22: recurrent | F22: emetteur | G22: Amortisation of intangibles from the Beta PPA
A23: gamma-ppa-amort | B23: 0 | C23: 23 | D23: 23 | E23: recurrent | F23: emetteur | G23: Amortisation of intangibles from the Gamma PPA
A24: dette-acquisition-interets | B24: 0 | C24: 0 | D24: 14 | E24: recurrent | F24: emetteur | G24: Interest on the acquisition debt
A25: litige-provision-2025 | B25: 18 | C25: 18 | D25: 18 | E25: oneOff | F25: omnium | G25: Isolated litigation provision, not restated by the issuer
A26: impot sur retraitements | D26: -26
A28: LES TROIS BASES — calculees, jamais saisies
A29: base | B29: ebitda | C29: ebit | D29: net | E29: moteur (net)
A30: Omnium (publie + vrais one-offs) | B30: =pub_ebitda+SUMIF($E$21:$E$25,"oneOff",B$21:B$25) | C30: =pub_ebit+SUMIF($E$21:$E$25,"oneOff",C$21:C$25) | D30: =pub_net+SUMIF($E$21:$E$25,"oneOff",D$21:D$25)+impotRet*SUMIF($E$21:$E$25,"oneOff",$D$21:$D$25)/SUM($D$21:$D$25) | E30: 135.73
A31: Ajuste du management (+ recurrents) | B31: =pub_ebitda+SUM(B$21:B$25) | C31: =pub_ebit+SUM(C$21:C$25) | D31: =pub_net+SUM(D$21:D$25)+impotRet | E31: 178
A32: Coin = recurrents-deguises | B32: =SUMIF($E$21:$E$25,"recurrent",B$21:B$25) | C32: =SUMIF($E$21:$E$25,"recurrent",C$21:C$25) | D32: =SUMIF($E$21:$E$25,"recurrent",D$21:D$25)+impotRet*SUMIF($E$21:$E$25,"recurrent",$D$21:$D$25)/SUM($D$21:$D$25) | E32: 60.27
A33: ajuste PUBLIE par la societe (cible de bouclage) | B33: 425 | C33: 300 | D33: 178
A34: BOUCLAGE | B34: =IF(ABS(B32-ajPub_ebitda)<=MAX(1,ABS(ajPub_ebitda)*0.005),"OK","NE BOUCLE PAS") | C34: =IF(ABS(C32-ajPub_ebit)<=MAX(1,ABS(ajPub_ebit)*0.005),"OK","NE BOUCLE PAS") | D34: =IF(ABS(D32-ajPub_net)<=MAX(1,ABS(ajPub_net)*0.005),"OK","NE BOUCLE PAS")

Sheet Modele
A1: MODELE — chaque cellule est une formule sur des variables nommees
A2: ligne | B2: 2025 | C2: 2026 | D2: 2027 | E2: 2028 | F2: 2029 | G2: 2030 | I2: 2026 | J2: 2027 | K2: 2028 | L2: 2029 | M2: 2030
A3: Chiffre d'affaires | B3: 2000 | C3: =B3*(1+g_2026) | D3: =C3*(1+g_2027) | E3: =D3*(1+g_2028) | F3: =E3*(1+g_2029) | G3: =F3*(1+g_2030) | I3: 2060 | J3: 1936.4 | K3: 2013.856 | L3: 2104.4795 | M3: 2199.1811
A4: Croissance | C4: =g_2026 | D4: =g_2027 | E4: =g_2028 | F4: =g_2029 | G4: =g_2030 | I4: 0.03 | J4: -0.06 | K4: 0.04 | L4: 0.045 | M4: 0.045
A5: Marge d'EBITDA | C5: =marge_2026 | D5: =marge_2027 | E5: =marge_2028 | F5: =marge_2029 | G5: =marge_2030 | I5: 0.192 | J5: 0.15 | K5: 0.178 | L5: 0.19 | M5: 0.195
A6: EBITDA | B6: 380 | C6: =C3*C5 | D6: =D3*D5 | E6: =E3*E5 | F6: =F3*F5 | G6: =G3*G5 | I6: 395.52 | J6: 290.46 | K6: 358.4664 | L6: 399.8511 | M6: 428.8403
A7: dotations hors PPA | B7: 190 | C7: =B7+B3*capexRatio/dureeAmort | D7: =C7+C3*capexRatio/dureeAmort | E7: =D7+D3*capexRatio/dureeAmort | F7: =E7+E3*capexRatio/dureeAmort | G7: =F7+F3*capexRatio/dureeAmort | I7: 202.2222 | J7: 214.8111 | K7: 226.6447 | L7: 238.9516 | M7: 251.8123
A8: amortissement du PPA | B8: 0 | C8: =73.0 | D8: =65.0 | E8: =50.0 | F8: =32.0 | G8: =22.0 | I8: 73 | J8: 65 | K8: 50 | L8: 32 | M8: 22
A9: Dotations | B9: -190 | C9: =-(C7+C8) | D9: =-(D7+D8) | E9: =-(E7+E8) | F9: =-(F7+F8) | G9: =-(G7+G8) | I9: -275.2222 | J9: -279.8111 | K9: -276.6447 | L9: -270.9516 | M9: -273.8123
A10: EBIT | B10: 190 | C10: =C6+C9 | D10: =D6+D9 | E10: =E6+E9 | F10: =F6+F9 | G10: =G6+G9 | I10: 120.2978 | J10: 10.6489 | K10: 81.8217 | L10: 128.8995 | M10: 155.028
A11: Dette brute | B11: 1150 | C11: =B11 | D11: =C11 | E11: =D11 | F11: =E11 | G11: =F11
A12: Tresorerie | B12: 180 | C12: =B12+C19-C22-B3*capexRatio-C9 | D12: =C12+D19-D22-C3*capexRatio-D9 | E12: =D12+E19-E22-D3*capexRatio-E9 | F12: =E12+F19-F22-E3*capexRatio-F9 | G12: =F12+G19-G22-F3*capexRatio-G9
A13: Dette locative | B13: 240 | C13: =B13 | D13: =C13 | E13: =D13 | F13: =E13 | G13: =F13
A14: Resultat financier (rang 2) | B14: -48 | C14: =-(B11*tauxDette)+B12*tauxCash-(B13*tauxLease) | D14: =-(C11*tauxDette)+C12*tauxCash-(C13*tauxLease) | E14: =-(D11*tauxDette)+D12*tauxCash-(D13*tauxLease) | F14: =-(E11*tauxDette)+E12*tauxCash-(E13*tauxLease) | G14: =-(F11*tauxDette)+F12*tauxCash-(F13*tauxLease) | I14: -61.08 | J14: -57.6829 | K14: -55.2048 | L14: -51.9559 | M14: -48.5341
A15: Resultat avant impot | B15: 142 | C15: =C10+C14 | D15: =D10+D14 | E15: =E10+E14 | F15: =F10+F14 | G15: =G10+G14 | I15: 59.2178 | J15: -47.034 | K15: 26.6169 | L15: 76.9436 | M15: 106.494
A16: Taux d'impot applique | C16: =tauxIS_2026 | D16: =tauxIS_2027 | E16: =tauxIS_2028 | F16: =tauxIS_2029 | G16: =tauxIS_2030 | I16: 0.27 | J16: 0.285 | K16: 0.285 | L16: 0.285 | M16: 0.285
A17: Impot | B17: -40 | C17: =-C15*C16 | D17: -6 | E17: =-E15*E16 | F17: =-F15*F16 | G17: =-G15*G16 | I17: -15.9888 | J17: -6 | K17: -7.5858 | L17: -21.9289 | M17: -30.3508
A18: Minoritaires | B18: -22 | C18: =partMinos*(C15+C17) | D18: =partMinos*(D15+D17) | E18: =partMinos*(E15+E17) | F18: =partMinos*(F15+F17) | G18: =partMinos*(G15+G17) | I18: -11.888 | J18: 14.5844 | K18: -5.2336 | L18: -15.129 | M18: -20.9394
A19: Resultat net | B19: 80 | C19: =C15+C17+C18 | D19: =D15+D17+D18 | E19: =E15+E17+E18 | F19: =F15+F17+F18 | G19: =G15+G17+G18 | I19: 31.341 | J19: -38.4497 | K19: 13.7976 | L19: 39.8856 | M19: 55.2038
A20: Actions (millions) | B20: 64 | C20: =B20*(1-rachatPct) | D20: =C20*(1-rachatPct) | E20: =D20*(1-rachatPct) | F20: =E20*(1-rachatPct) | G20: =F20*(1-rachatPct) | I20: 63.488 | J20: 62.9801 | K20: 62.4763 | L20: 61.9764 | M20: 61.4806
A21: BPA | B21: 1.25 | C21: =C19/C20 | D21: =D19/D20 | E21: =E19/E20 | F21: =F19/F20 | G21: =G19/G20 | I21: 0.4937 | J21: -0.6105 | K21: 0.2208 | L21: 0.6436 | M21: 0.8979
A22: Dividende verse | C22: =C19*tauxDistrib | D22: =D19*tauxDistrib | E22: =E19*tauxDistrib | F22: =F19*tauxDistrib | G22: =G19*tauxDistrib | I22: 7.8353 | J22: -9.6124 | K22: 3.4494 | L22: 9.9714 | M22: 13.801
A24: RANG DU MOTEUR — d'ou vient chaque hypothese
A25: croissance | C25: guidance | D25: implicite | E25: normatif | F25: normatif | G25: normatif
A26: marge | C26: guidance | D26: implicite | E26: implicite | F26: normatif | G26: normatif
A27: taux d'impot | C27: guidance | D27: override | E27: normatif | F27: normatif | G27: normatif
A28: resultat financier | C28: 2 | D28: 2 | E28: 2 | F28: 2 | G28: 2

Sheet Controles
A1: CONTROLES — la feuille est son propre test de non-regression
A2: formule vs moteur | B2: 2026 | C2: 2027 | D2: 2028 | E2: 2029 | F2: 2030
A3: Chiffre d'affaires | B3: =IF(ABS(Modele!C3-Modele!I3)<0.01,"OK","ECART "&TEXT(Modele!C3-Modele!I3,"0.00")) | C3: =IF(ABS(Modele!D3-Modele!J3)<0.01,"OK","ECART "&TEXT(Modele!D3-Modele!J3,"0.00")) | D3: =IF(ABS(Modele!E3-Modele!K3)<0.01,"OK","ECART "&TEXT(Modele!E3-Modele!K3,"0.00")) | E3: =IF(ABS(Modele!F3-Modele!L3)<0.01,"OK","ECART "&TEXT(Modele!F3-Modele!L3,"0.00")) | F3: =IF(ABS(Modele!G3-Modele!M3)<0.01,"OK","ECART "&TEXT(Modele!G3-Modele!M3,"0.00"))
A4: EBITDA | B4: =IF(ABS(Modele!C6-Modele!I6)<0.01,"OK","ECART "&TEXT(Modele!C6-Modele!I6,"0.00")) | C4: =IF(ABS(Modele!D6-Modele!J6)<0.01,"OK","ECART "&TEXT(Modele!D6-Modele!J6,"0.00")) | D4: =IF(ABS(Modele!E6-Modele!K6)<0.01,"OK","ECART "&TEXT(Modele!E6-Modele!K6,"0.00")) | E4: =IF(ABS(Modele!F6-Modele!L6)<0.01,"OK","ECART "&TEXT(Modele!F6-Modele!L6,"0.00")) | F4: =IF(ABS(Modele!G6-Modele!M6)<0.01,"OK","ECART "&TEXT(Modele!G6-Modele!M6,"0.00"))
A5: EBIT | B5: =IF(ABS(Modele!C10-Modele!I10)<0.01,"OK","ECART "&TEXT(Modele!C10-Modele!I10,"0.00")) | C5: =IF(ABS(Modele!D10-Modele!J10)<0.01,"OK","ECART "&TEXT(Modele!D10-Modele!J10,"0.00")) | D5: =IF(ABS(Modele!E10-Modele!K10)<0.01,"OK","ECART "&TEXT(Modele!E10-Modele!K10,"0.00")) | E5: =IF(ABS(Modele!F10-Modele!L10)<0.01,"OK","ECART "&TEXT(Modele!F10-Modele!L10,"0.00")) | F5: =IF(ABS(Modele!G10-Modele!M10)<0.01,"OK","ECART "&TEXT(Modele!G10-Modele!M10,"0.00"))
A6: Resultat avant impot | B6: =IF(ABS(Modele!C15-Modele!I15)<0.01,"OK","ECART "&TEXT(Modele!C15-Modele!I15,"0.00")) | C6: =IF(ABS(Modele!D15-Modele!J15)<0.01,"OK","ECART "&TEXT(Modele!D15-Modele!J15,"0.00")) | D6: =IF(ABS(Modele!E15-Modele!K15)<0.01,"OK","ECART "&TEXT(Modele!E15-Modele!K15,"0.00")) | E6: =IF(ABS(Modele!F15-Modele!L15)<0.01,"OK","ECART "&TEXT(Modele!F15-Modele!L15,"0.00")) | F6: =IF(ABS(Modele!G15-Modele!M15)<0.01,"OK","ECART "&TEXT(Modele!G15-Modele!M15,"0.00"))
A7: Impot | B7: =IF(ABS(Modele!C17-Modele!I17)<0.01,"OK","ECART "&TEXT(Modele!C17-Modele!I17,"0.00")) | C7: =IF(ABS(Modele!D17-Modele!J17)<0.01,"OK","ECART "&TEXT(Modele!D17-Modele!J17,"0.00")) | D7: =IF(ABS(Modele!E17-Modele!K17)<0.01,"OK","ECART "&TEXT(Modele!E17-Modele!K17,"0.00")) | E7: =IF(ABS(Modele!F17-Modele!L17)<0.01,"OK","ECART "&TEXT(Modele!F17-Modele!L17,"0.00")) | F7: =IF(ABS(Modele!G17-Modele!M17)<0.01,"OK","ECART "&TEXT(Modele!G17-Modele!M17,"0.00"))
A8: Resultat net | B8: =IF(ABS(Modele!C19-Modele!I19)<0.01,"OK","ECART "&TEXT(Modele!C19-Modele!I19,"0.00")) | C8: =IF(ABS(Modele!D19-Modele!J19)<0.01,"OK","ECART "&TEXT(Modele!D19-Modele!J19,"0.00")) | D8: =IF(ABS(Modele!E19-Modele!K19)<0.01,"OK","ECART "&TEXT(Modele!E19-Modele!K19,"0.00")) | E8: =IF(ABS(Modele!F19-Modele!L19)<0.01,"OK","ECART "&TEXT(Modele!F19-Modele!L19,"0.00")) | F8: =IF(ABS(Modele!G19-Modele!M19)<0.01,"OK","ECART "&TEXT(Modele!G19-Modele!M19,"0.00"))
A9: BPA | B9: =IF(ABS(Modele!C21-Modele!I21)<0.01,"OK","ECART "&TEXT(Modele!C21-Modele!I21,"0.00")) | C9: =IF(ABS(Modele!D21-Modele!J21)<0.01,"OK","ECART "&TEXT(Modele!D21-Modele!J21,"0.00")) | D9: =IF(ABS(Modele!E21-Modele!K21)<0.01,"OK","ECART "&TEXT(Modele!E21-Modele!K21,"0.00")) | E9: =IF(ABS(Modele!F21-Modele!L21)<0.01,"OK","ECART "&TEXT(Modele!F21-Modele!L21,"0.00")) | F9: =IF(ABS(Modele!G21-Modele!M21)<0.01,"OK","ECART "&TEXT(Modele!G21-Modele!M21,"0.00"))
A11: GARDE-FOUS
A12: Aucune cellule orpheline (regle 5) | B12: =IF(COUNTBLANK(Hypotheses!$C$3:$C$27)=0,"OK","MOTEUR MANQUANT")
A13: Devise de reporting = devise de cotation (prop. 6) | B13: =IF(EXACT('Lisez-moi'!B10,'Lisez-moi'!B11),"OK","P/E INTERDIT SANS TAUX DATE")
A15: Colonne 'moteur' de la feuille Modele = valeur produite par engine/model.py. Toute divergence est une erreur de traduction, pas une tolerance.
