Workbook
Name g_2026: 'Hypotheses'!$C$3
Name g_2027: 'Hypotheses'!$C$4
Name g_2028: 'Hypotheses'!$C$5
Name marge_2026: 'Hypotheses'!$C$6
Name marge_2027: 'Hypotheses'!$C$7
Name marge_2028: 'Hypotheses'!$C$8
Name tauxIS_2026: 'Hypotheses'!$C$9
Name tauxIS_2027: 'Hypotheses'!$C$10
Name tauxIS_2028: 'Hypotheses'!$C$11
Name capexRatio: 'Hypotheses'!$C$12
Name dureeAmort: 'Hypotheses'!$C$13
Name spreadNormatif: 'Hypotheses'!$C$14
Name rachatPct: 'Hypotheses'!$C$15
Name tauxDistrib: 'Hypotheses'!$C$16
Name gTerminal: 'Hypotheses'!$C$17
Name margeTerminale: 'Hypotheses'!$C$18
Name partMinos: 'Hypotheses'!$C$19
Name pub_ca: 'Historique'!$B$3
Name pub_margeBrute: 'Historique'!$B$4
Name pub_ebitda: 'Historique'!$B$5
Name pub_da: 'Historique'!$B$6
Name pub_ebit: 'Historique'!$B$7
Name pub_finNet: 'Historique'!$B$8
Name pub_avantImpot: 'Historique'!$B$9
Name pub_impot: 'Historique'!$B$10
Name pub_minoritaires: 'Historique'!$B$11
Name pub_net: 'Historique'!$B$12
Name impotRet: 'Historique'!$D$21
Name CA_2025: 'Modele'!$B$3
Name CA_2026: 'Modele'!$C$3
Name CA_2027: 'Modele'!$D$3
Name CA_2028: 'Modele'!$E$3
Name dette_2025: 'Modele'!$B$11
Name dette_2026: 'Modele'!$C$11
Name dette_2027: 'Modele'!$D$11
Name dette_2028: 'Modele'!$E$11
Name cash_2025: 'Modele'!$B$12
Name cash_2026: 'Modele'!$C$12
Name cash_2027: 'Modele'!$D$12
Name cash_2028: 'Modele'!$E$12

Sheet Lisez-moi
A1: Simple SA — moteur v1.0.0 — empreinte 1751db17c7aa
A3: Ce que contient ce fichier | B3: Les FORMULES du moteur, pas ses resultats. Chaque cellule calculee est une formule ecrite sur des variables nommees, lisible et modifiable.
A4: Le test integre | B4: Colonne 'moteur' = la valeur produite par engine/model.py. La feuille Controles compare formule et moteur ligne a ligne : un ecart s'affiche a l'ouverture.
A5: Peremption | B5: Une hypothese de rang 'guidance' ne vaut QUE pour son exercice. Au-dela le moteur bascule sur le normatif - visible dans la colonne rang de la feuille Modele.
A6: Rang du resultat financier | B6: 1 = detail publie par instrument. 2 = taux appliques aux postes de bilan decomposes. 3 = spread normatif sur la dette nette. La valeur est retournee AVEC son rang.
A7: Base Omnium | B7: publie + vrais one-offs nets d'impot. L'ajuste du management ajoute en plus les recurrents-deguises : c'est le coin, et Omnium le GARDE.
A8: Si l'empreinte ne correspond plus | B8: Les entrees ont change depuis la generation : cette feuille est perimee, regenerez-la.
A10: Devise de reporting | B10: EUR
A11: Devise de cotation | B11: EUR
A12: Cours | B12: 60.0 au 2026-08-22

Sheet Hypotheses
A1: MOTEURS — toute cellule projetee est pilotee par l'un d'eux
A2: moteur | B2: variable | C2: valeur | D2: rang | E2: expire | F2: justification / source
A3: Croissance du CA 2026 | B3: g_2026 | C3: 0.05 | D3: normatif | E3: — | F3: Croissance de marche, aucune guidance publiee
A4: Croissance du CA 2027 | B4: g_2027 | C4: 0.05 | D4: normatif | E4: — | F4: Croissance de marche, aucune guidance publiee
A5: Croissance du CA 2028 | B5: g_2028 | C5: 0.05 | D5: normatif | E5: — | F5: Croissance de marche, aucune guidance publiee
A6: Marge d'EBITDA 2026 | B6: marge_2026 | C6: 0.2 | D6: normatif | E6: — | F6: Marge stable au niveau observe
A7: Marge d'EBITDA 2027 | B7: marge_2027 | C7: 0.2 | D7: normatif | E7: — | F7: Marge stable au niveau observe
A8: Marge d'EBITDA 2028 | B8: marge_2028 | C8: 0.2 | D8: normatif | E8: — | F8: Marge stable au niveau observe
A9: Taux d'impot 2026 | B9: tauxIS_2026 | C9: 0.25 | D9: normatif | E9: — | F9: Taux effectif observe, stable
A10: Taux d'impot 2027 | B10: tauxIS_2027 | C10: 0.25 | D10: normatif | E10: — | F10: Taux effectif observe, stable
A11: Taux d'impot 2028 | B11: tauxIS_2028 | C11: 0.25 | D11: normatif | E11: — | F11: Taux effectif observe, stable
A12: Capex / CA | B12: capexRatio | C12: 0.04 | D12: normatif | E12: — | F12: Capex normatif, stable
A13: Duree d'amortissement | B13: dureeAmort | C13: 10 | D13: normatif | E13: — | F13: Duree implicite du parc
A14: Spread normatif sur dette nette | B14: spreadNormatif | C14: 0.05 | D14: rang 3 | E14: — | F14: Rang 3 : spread normatif applique a la dette nette, aucun detail publie par instrument
... A19: Minoritaires / resultat | B19: partMinos | C19: 0 | D19: normatif | E19: — | F19: Part des minoritaires observee au dernier exercice publie, reconduite

Sheet Historique
A1: ECHELLE PUBLIEE 2025-FY — un modele unique, les barreaux non publies restent vides
A2: barreau | B2: publie
A3: ca | B3: 500
A4: margeBrute | B4: 300
A5: ebitda | B5: 100
A6: da | B6: -20
A7: ebit | B7: 80
A8: finNet | B8: -5
A9: avantImpot | B9: 75
A10: impot | B10: -18.75
A11: minoritaires | B11: 0
A12: net | B12: 56.25
A14: IDENTITES DE L'ECHELLE
A15: ebitda + da = ebit | B15: =pub_ebitda+pub_da-pub_ebit | C15: =IF(ABS(B15)<=MAX(1,ABS(pub_ebit)*0.005),"OK","ECART")
A16: ebit + finNet = avantImpot | B16: =pub_ebit+pub_finNet-pub_avantImpot | C16: =IF(ABS(B16)<=MAX(1,ABS(pub_avantImpot)*0.005),"OK","ECART")
A17: avantImpot + impot + minoritaires = net | B17: =pub_avantImpot+pub_impot+pub_minoritaires-pub_net | C17: =IF(ABS(B17)<=MAX(1,ABS(pub_net)*0.005),"OK","ECART")
A19: RETRAITEMENTS — la table de l'emetteur, ligne a ligne
A20: ligne | B20: ebitda | C20: ebit | D20: net | E20: classe | F20: origine | G20: libelle
A21: impot sur retraitements | D21: 0
A23: LES TROIS BASES — calculees, jamais saisies
A24: base | B24: ebitda | C24: ebit | D24: net | E24: moteur (net)
A25: Omnium (publie + vrais one-offs) | B25: =pub_ebitda+SUMIF($E$21:$E$20,"oneOff",B$21:B$20) | C25: =pub_ebit+SUMIF($E$21:$E$20,"oneOff",C$21:C$20) | D25: =pub_net+SUMIF($E$21:$E$20,"oneOff",D$21:D$20)+impotRet*SUMIF($E$21:$E$20,"oneOff",$D$21:$D$20)/SUM($D$21:$D$20) | E25: 56.25
A26: Ajuste du management (+ recurrents) | B26: =pub_ebitda+SUM(B$21:B$20) | C26: =pub_ebit+SUM(C$21:C$20) | D26: =pub_net+SUM(D$21:D$20)+impotRet | E26: 56.25
A27: Coin = recurrents-deguises | B27: =SUMIF($E$21:$E$20,"recurrent",B$21:B$20) | C27: =SUMIF($E$21:$E$20,"recurrent",C$21:C$20) | D27: =SUMIF($E$21:$E$20,"recurrent",D$21:D$20)+impotRet*SUMIF($E$21:$E$20,"recurrent",$D$21:$D$20)/SUM($D$21:$D$20) | E27: 0
A28: ajuste PUBLIE par la societe (cible de bouclage)
A29: BOUCLAGE

Sheet Modele
A1: MODELE — chaque cellule est une formule sur des variables nommees
A2: ligne | B2: 2025 | C2: 2026 | D2: 2027 | E2: 2028 | G2: 2026 | H2: 2027 | I2: 2028
A3: Chiffre d'affaires | B3: 500 | C3: =B3*(1+g_2026) | D3: =C3*(1+g_2027) | E3: =D3*(1+g_2028) | G3: 525 | H3: 551.25 | I3: 578.8125
A4: Croissance | C4: =g_2026 | D4: =g_2027 | E4: =g_2028 | G4: 0.05 | H4: 0.05 | I4: 0.05
A5: Marge d'EBITDA | C5: =marge_2026 | D5: =marge_2027 | E5: =marge_2028 | G5: 0.2 | H5: 0.2 | I5: 0.2
A6: EBITDA | B6: 100 | C6: =C3*C5 | D6: =D3*D5 | E6: =E3*E5 | G6: 105 | H6: 110.25 | I6: 115.7625
A7: dotations hors PPA | B7: 20 | C7: =B7+B3*capexRatio/dureeAmort | D7: =C7+C3*capexRatio/dureeAmort | E7: =D7+D3*capexRatio/dureeAmort | G7: 22 | H7: 24.1 | I7: 26.305
A8: amortissement du PPA | B8: 0 | C8: =0 | D8: =0 | E8: =0 | G8: 0 | H8: 0 | I8: 0
A9: Dotations | B9: -20 | C9: =-(C7+C8) | D9: =-(D7+D8) | E9: =-(E7+E8) | G9: -22 | H9: -24.1 | I9: -26.305
A10: EBIT | B10: 80 | C10: =C6+C9 | D10: =D6+D9 | E10: =E6+E9 | G10: 83 | H10: 86.15 | I10: 89.4575
A11: Dette brute | B11: 150 | C11: =B11 | D11: =C11 | E11: =D11
A12: Tresorerie | B12: 50 | C12: =B12+C19-C22-B3*capexRatio-C9 | D12: =C12+D19-D22-C3*capexRatio-D9 | E12: =D12+E19-E22-D3*capexRatio-E9
A13: Dette locative | B13: 0 | C13: =B13 | D13: =C13 | E13: =D13
A14: Resultat financier (rang 3) | B14: -5 | C14: =-(B11-B12+B13)*spreadNormatif | D14: =-(C11-C12+C13)*spreadNormatif | E14: =-(D11-D12+D13)*spreadNormatif | G14: -5 | H14: -3.145 | I14: -1.1224
A15: Resultat avant impot | B15: 75 | C15: =C10+C14 | D15: =D10+D14 | E15: =E10+E14 | G15: 78 | H15: 83.005 | I15: 88.3351
A16: Taux d'impot applique | C16: =tauxIS_2026 | D16: =tauxIS_2027 | E16: =tauxIS_2028 | G16: 0.25 | H16: 0.25 | I16: 0.25
A17: Impot | B17: -18.75 | C17: =-C15*C16 | D17: =-D15*D16 | E17: =-E15*E16 | G17: -19.5 | H17: -20.7513 | I17: -22.0838
A18: Minoritaires | B18: 0 | C18: =partMinos*(C15+C17) | D18: =partMinos*(D15+D17) | E18: =partMinos*(E15+E17) | G18: 0 | H18: 0 | I18: 0
A19: Resultat net | B19: 56.25 | C19: =C15+C17+C18 | D19: =D15+D17+D18 | E19: =E15+E17+E18 | G19: 58.5 | H19: 62.2538 | I19: 66.2513
A20: Actions (millions) | B20: 25 | C20: =B20*(1-rachatPct) | D20: =C20*(1-rachatPct) | E20: =D20*(1-rachatPct) | G20: 25 | H20: 25 | I20: 25
A21: BPA | B21: 2.25 | C21: =C19/C20 | D21: =D19/D20 | E21: =E19/E20 | G21: 2.34 | H21: 2.4902 | I21: 2.6501
A22: Dividende verse | C22: =C19*tauxDistrib | D22: =D19*tauxDistrib | E22: =E19*tauxDistrib | G22: 23.4 | H22: 24.9015 | I22: 26.5005
A24: RANG DU MOTEUR — d'ou vient chaque hypothese
A25: croissance | C25: normatif | D25: normatif | E25: normatif
A26: marge | C26: normatif | D26: normatif | E26: normatif
A27: taux d'impot | C27: normatif | D27: normatif | E27: normatif
A28: resultat financier | C28: 3 | D28: 3 | E28: 3

Sheet Controles
A1: CONTROLES — la feuille est son propre test de non-regression
A2: formule vs moteur | B2: 2026 | C2: 2027 | D2: 2028
A3: Chiffre d'affaires | B3: =IF(ABS(Modele!C3-Modele!G3)<0.01,"OK","ECART "&TEXT(Modele!C3-Modele!G3,"0.00")) | C3: =IF(ABS(Modele!D3-Modele!H3)<0.01,"OK","ECART "&TEXT(Modele!D3-Modele!H3,"0.00")) | D3: =IF(ABS(Modele!E3-Modele!I3)<0.01,"OK","ECART "&TEXT(Modele!E3-Modele!I3,"0.00"))
A4: EBITDA | B4: =IF(ABS(Modele!C6-Modele!G6)<0.01,"OK","ECART "&TEXT(Modele!C6-Modele!G6,"0.00")) | C4: =IF(ABS(Modele!D6-Modele!H6)<0.01,"OK","ECART "&TEXT(Modele!D6-Modele!H6,"0.00")) | D4: =IF(ABS(Modele!E6-Modele!I6)<0.01,"OK","ECART "&TEXT(Modele!E6-Modele!I6,"0.00"))
A5: EBIT | B5: =IF(ABS(Modele!C10-Modele!G10)<0.01,"OK","ECART "&TEXT(Modele!C10-Modele!G10,"0.00")) | C5: =IF(ABS(Modele!D10-Modele!H10)<0.01,"OK","ECART "&TEXT(Modele!D10-Modele!H10,"0.00")) | D5: =IF(ABS(Modele!E10-Modele!I10)<0.01,"OK","ECART "&TEXT(Modele!E10-Modele!I10,"0.00"))
A6: Resultat avant impot | B6: =IF(ABS(Modele!C15-Modele!G15)<0.01,"OK","ECART "&TEXT(Modele!C15-Modele!G15,"0.00")) | C6: =IF(ABS(Modele!D15-Modele!H15)<0.01,"OK","ECART "&TEXT(Modele!D15-Modele!H15,"0.00")) | D6: =IF(ABS(Modele!E15-Modele!I15)<0.01,"OK","ECART "&TEXT(Modele!E15-Modele!I15,"0.00"))
A7: Impot | B7: =IF(ABS(Modele!C17-Modele!G17)<0.01,"OK","ECART "&TEXT(Modele!C17-Modele!G17,"0.00")) | C7: =IF(ABS(Modele!D17-Modele!H17)<0.01,"OK","ECART "&TEXT(Modele!D17-Modele!H17,"0.00")) | D7: =IF(ABS(Modele!E17-Modele!I17)<0.01,"OK","ECART "&TEXT(Modele!E17-Modele!I17,"0.00"))
A8: Resultat net | B8: =IF(ABS(Modele!C19-Modele!G19)<0.01,"OK","ECART "&TEXT(Modele!C19-Modele!G19,"0.00")) | C8: =IF(ABS(Modele!D19-Modele!H19)<0.01,"OK","ECART "&TEXT(Modele!D19-Modele!H19,"0.00")) | D8: =IF(ABS(Modele!E19-Modele!I19)<0.01,"OK","ECART "&TEXT(Modele!E19-Modele!I19,"0.00"))
A9: BPA | B9: =IF(ABS(Modele!C21-Modele!G21)<0.01,"OK","ECART "&TEXT(Modele!C21-Modele!G21,"0.00")) | C9: =IF(ABS(Modele!D21-Modele!H21)<0.01,"OK","ECART "&TEXT(Modele!D21-Modele!H21,"0.00")) | D9: =IF(ABS(Modele!E21-Modele!I21)<0.01,"OK","ECART "&TEXT(Modele!E21-Modele!I21,"0.00"))
A11: GARDE-FOUS
A12: Aucune cellule orpheline (regle 5) | B12: =IF(COUNTBLANK(Hypotheses!$C$3:$C$17)=0,"OK","MOTEUR MANQUANT")
A13: Devise de reporting = devise de cotation (prop. 6) | B13: =IF(EXACT('Lisez-moi'!B10,'Lisez-moi'!B11),"OK","P/E INTERDIT SANS TAUX DATE")
A15: Colonne 'moteur' de la feuille Modele = valeur produite par engine/model.py. Toute divergence est une erreur de traduction, pas une tolerance.
